sos_papermill/__init__.py
sos_papermill/_version.py
sos_papermill/engine.py
sos_papermill-0.2.1.dist-info/LICENSE
sos_papermill-0.2.1.dist-info/METADATA
sos_papermill-0.2.1.dist-info/WHEEL
sos_papermill-0.2.1.dist-info/entry_points.txt
sos_papermill-0.2.1.dist-info/top_level.txt
sos_papermill-0.2.1.dist-info/RECORD
