Metadata-Version: 2.1
Name: sos-papermill
Version: 0.2.1
Summary: SoS extension for papermill
Home-page: https://github.com/vatlab/sos-papermill
Author: Bo Peng
Author-email: bpeng@mdanderson.org
Maintainer: Bo Peng
Maintainer-email: bpeng@mdanderson.org
License: 3-clause BSD
Platform: UNKNOWN
Classifier: Development Status :: 4 - Beta
Classifier: Environment :: Console
Classifier: License :: OSI Approved :: BSD License
Classifier: Natural Language :: English
Classifier: Operating System :: POSIX :: Linux
Classifier: Operating System :: MacOS :: MacOS X
Classifier: Operating System :: Microsoft :: Windows
Classifier: Intended Audience :: Information Technology
Classifier: Intended Audience :: Science/Research
Classifier: Programming Language :: Python :: 3 :: Only
Classifier: Programming Language :: Python :: 3.6
Classifier: Programming Language :: Python :: 3.7
Classifier: Programming Language :: Python :: 3.8
Classifier: Programming Language :: Python :: Implementation :: CPython
Classifier: Programming Language :: Python :: Implementation :: PyPy
Requires-Python: >=3.6
Requires-Dist: papermill (>=2.0.0)
Requires-Dist: sos (>=0.20.2)
Requires-Dist: sos-notebook (>=0.20.4)
